{
  "name": "DOGE REFLECTIONS",
  "symbol": "DR",
  "decimals": 9,
  "description": "Establishing an Ecosystem of Binance Smart Chain reflectionary tokens, all supporting each other while helping you to diversify your portfolio with passive income through your favorite projects and now we have added Dogecoin to the list of rewards!",
  "discord": "",
  "telegram": "https://t.me/bscreflectors",
  "twitter": "https://twitter.com/bscreflectors",
  "website": "https://bscreflectors.com/",
  "vested": [],
  "audits": [],
  "explorer": "https://bscscan.com/token/0x39c67CfA7F179B686177e6085D51C9d544f1A198",
  "id": "0x39c67CfA7F179B686177e6085D51C9d544f1A198"
}